Metadata-Version: 2.4
Name: pystacker
Version: 1.9.2
Summary: Stacker: RPN Calculator in Python
Author: remokasu
License: MIT License
Project-URL: Homepage, https://github.com/remokasu/stacker
Keywords: reverse-polish-calculator,rpn,terminal-app
Requires-Python: >=3.10
License-File: LICENSE
Requires-Dist: prompt-toolkit>=3.0.0
Dynamic: license-file
